medenv/__init__.py
medenv/cmems.py
medenv/etopo.py
medenv/utils.py
medenv/woa.py
medenv-1.1.0.dist-info/LICENSE
medenv-1.1.0.dist-info/METADATA
medenv-1.1.0.dist-info/WHEEL
medenv-1.1.0.dist-info/top_level.txt
medenv-1.1.0.dist-info/RECORD
