Metadata-Version: 2.1
Name: medenv
Version: 1.1.0
License-File: LICENSE
Requires-Dist: netCDF4 >=1.5.8
Requires-Dist: tqdm >=4.66.1
Requires-Dist: pandas >=2.1.3
Requires-Dist: xarray >=2023.11.0
Requires-Dist: lxml >=4.9.3
Requires-Dist: copernicusmarine >=1.0.2
